sqlalchemy_profile/__init__.py
sqlalchemy_profile/api.py
sqlalchemy_profile/profile.py
sqlalchemy_profile/tests/__init__.py
sqlalchemy_profile/tests/test_api.py
sqlalchemy_profile/tests/test_profile.py
sqlalchemy_profile-0.1.0.dist-info/DESCRIPTION.rst
sqlalchemy_profile-0.1.0.dist-info/METADATA
sqlalchemy_profile-0.1.0.dist-info/RECORD
sqlalchemy_profile-0.1.0.dist-info/WHEEL
sqlalchemy_profile-0.1.0.dist-info/metadata.json
sqlalchemy_profile-0.1.0.dist-info/top_level.txt
